pyloadnprep/__init__.py
pyloadnprep/feature_importance.py
pyloadnprep/preprocessing.py
pyloadnprep/run.py
pyloadnprep/statistical_check_ups.py
pyloadnprep-0.0.4.dist-info/METADATA
pyloadnprep-0.0.4.dist-info/WHEEL
pyloadnprep-0.0.4.dist-info/top_level.txt
pyloadnprep-0.0.4.dist-info/RECORD
