Metadata-Version: 2.1
Name: pyloadnprep
Version: 0.0.4
Summary: A simple preprocessing package
Home-page: https://github.com/terri1102/pyloadnprep
Author: terri1102
Author-email: terricodes@gmail.com
License: UNKNOWN
Platform: UNKNOWN
Classifier: Programming Language :: Python :: 3
Classifier: License :: OSI Approved :: MIT License
Classifier: Operating System :: OS Independent
Requires-Python: >=3.6
Requires-Dist: pandas
Requires-Dist: numpy
Requires-Dist: mplfinance
Requires-Dist: pykrx
